setup.cfg
setup.py
pypeline/DB.py
pypeline/__init__.py
pypeline/_version.py
pypeline_db.egg-info/PKG-INFO
pypeline_db.egg-info/SOURCES.txt
pypeline_db.egg-info/dependency_links.txt
pypeline_db.egg-info/requires.txt
pypeline_db.egg-info/top_level.txt
test/test_pypeline.py